<?xml version="1.0"?>
<!DOCTYPE hibernate-mapping PUBLIC "-//Hibernate/Hibernate Mapping DTD 3.0//EN"
"http://www.hibernate.org/dtd/hibernate-mapping-3.0.dtd">
<!-- Generated 23-oct-2014 8:25:41 by Hibernate Tools 3.6.0 -->
<hibernate-mapping>
    <class name="POJOS.CntMmtipDoc" table="Cnt_MMTipDoc" schema="dbo" catalog="BD_SEGURIDAD">
        <id name="codDoc" type="string">
            <column name="CodDoc" length="2" />
            <generator class="assigned" />
        </id>
        <property name="nomDoc" type="string">
            <column name="NomDoc" length="100" not-null="true" />
        </property>
        <property name="dv" type="boolean">
            <column name="DV" not-null="true" />
        </property>
        <property name="minLength" type="int">
            <column name="MinLength" not-null="true" />
        </property>
    </class>
</hibernate-mapping>
